dmlcloud/__init__.py
dmlcloud/checkpoint.py
dmlcloud/metrics.py
dmlcloud/pipeline.py
dmlcloud/stage.py
dmlcloud/util/__init__.py
dmlcloud/util/argparse.py
dmlcloud/util/data.py
dmlcloud/util/distributed.py
dmlcloud/util/git.py
dmlcloud/util/logging.py
dmlcloud/util/project.py
dmlcloud/util/slurm.py
dmlcloud/util/tcp.py
dmlcloud/util/thirdparty.py
dmlcloud/util/wandb.py
dmlcloud-0.3.3.dist-info/LICENSE
dmlcloud-0.3.3.dist-info/METADATA
dmlcloud-0.3.3.dist-info/WHEEL
dmlcloud-0.3.3.dist-info/top_level.txt
dmlcloud-0.3.3.dist-info/RECORD
