Metadata-Version: 2.1
Name: dmlcloud
Version: 0.3.3
Summary: Distributed torch training using horovod and slurm
Author: Sebastian Hoffmann
License: BSD 3-Clause License
Project-URL: Repository, https://github.com/sehoffmann/dmlcloud
Keywords: pytorch,torch.distributed,slurm,distributed training,deep learning
Classifier: Development Status :: 3 - Alpha
Classifier: License :: OSI Approved :: BSD License
Classifier: Operating System :: MacOS
Classifier: Operating System :: POSIX :: Linux
Classifier: Programming Language :: Python :: 3.10
Classifier: Topic :: Scientific/Engineering :: Artificial Intelligence
Requires-Python: >=3.10
License-File: LICENSE
Requires-Dist: torch
Requires-Dist: numpy
Requires-Dist: xarray
Requires-Dist: progress-table <1.0.0,>=0.1.20
Requires-Dist: omegaconf
